brewmaster/__init__.py
brewmaster/brewmaster.py
brewmaster-0.0.3.dist-info/METADATA
brewmaster-0.0.3.dist-info/WHEEL
brewmaster-0.0.3.dist-info/top_level.txt
brewmaster-0.0.3.dist-info/RECORD
